advantech/__init__.py
advantech/edge/__init__.py
advantech/edge/dmi_info.py
advantech/edge/_internal/__init__.py
advantech/edge/_internal/_eapi/__init__.py
advantech/edge/_internal/_eapi/_eapi.py
advantech/edge/_internal/_eapi/_eapi_backlight.py
advantech/edge/_internal/_eapi/_eapi_disk_info.py
advantech/edge/_internal/_eapi/_eapi_etp.py
advantech/edge/_internal/_eapi/_eapi_functions.py
advantech/edge/_internal/_eapi/_eapi_gpio.py
advantech/edge/_internal/_eapi/_eapi_ids.py
advantech/edge/_internal/_eapi/_eapi_status.py
advantech/edge/_internal/_feature_provider/__init__.py
advantech/edge/_internal/_feature_provider/_feature_provider.py
advantech/edge/_internal/_feature_provider/_platform_info_data.py
advantech/edge/_internal/_susi_iot/__init__.py
advantech/edge/_internal/_susi_iot/_susi_iot.py
advantech/edge/_internal/_susi_iot/_susi_iot_functions.py
advantech/edge/_internal/_susi_iot/_susi_iot_gpio.py
advantech/edge/_internal/_susi_iot/_susi_iot_ids.py
advantech/edge/_internal/_susi_iot/_susi_iot_status.py
advantech/edge/devices/__init__.py
advantech/edge/devices/device.py
advantech/edge/features/__init__.py
advantech/edge/features/disk_info.py
advantech/edge/features/gpio.py
advantech/edge/features/memory.py
advantech/edge/features/onboard_sensors.py
advantech/edge/features/platform_information.py
advantech/edge/features/watchdog.py
advantech/edge/idevices/__init__.py
advantech/edge/idevices/idevice.py
advantech/edge/ifeatures/__init__.py
advantech/edge/ifeatures/idiskinfo.py
advantech/edge/ifeatures/ifeature.py
advantech/edge/ifeatures/igpio.py
advantech/edge/ifeatures/imemory.py
advantech/edge/ifeatures/ionboardsensors.py
advantech/edge/ifeatures/iplatforminformation.py
advantech/edge/ifeatures/iwatchdog.py
advantech_edge-1.0.1.dist-info/METADATA
advantech_edge-1.0.1.dist-info/WHEEL
advantech_edge-1.0.1.dist-info/top_level.txt
advantech_edge-1.0.1.dist-info/RECORD
