Metadata-Version: 2.1
Name: advantech_edge
Version: 1.0.1
Author: Advantech Co., Ltd.
Author-email: 
Requires-Dist: setuptools
